badgerdb/__init__.py
badgerdb/badger.py
badgerdb/libbadger.so
badgerdb-0.7.0.dist-info/METADATA
badgerdb-0.7.0.dist-info/WHEEL
badgerdb-0.7.0.dist-info/top_level.txt
badgerdb-0.7.0.dist-info/RECORD
