Metadata-Version: 2.2
Name: badgerdb
Version: 0.7.0
Summary: Python wrapper for BadgerDB
Author: Poorna Prakash SR
Author-email: poornaprakashsr@gmail.com
Classifier: Programming Language :: Python :: 3
Classifier: License :: OSI Approved :: MIT License
Classifier: Operating System :: OS Independent
Requires-Python: >=3.6
Dynamic: author
Dynamic: author-email
Dynamic: classifier
Dynamic: description
Dynamic: description-content-type
Dynamic: requires-python
Dynamic: summary
